momentumnet/__init__.py
momentumnet/exact_rep_pytorch.py
momentumnet/models.py
momentumnet/momentum_net.py
momentumnet/resnet_to_momentumnet.py
momentumnet/toy_datasets.py
momentumnet/trainer_CIFAR_10.py
momentumnet/trainer_imagenet.py
momentumnet-0.10.dist-info/LICENSE
momentumnet-0.10.dist-info/METADATA
momentumnet-0.10.dist-info/WHEEL
momentumnet-0.10.dist-info/top_level.txt
momentumnet-0.10.dist-info/RECORD
