Metadata-Version: 2.1
Name: momentumnet
Version: 0.10
Summary: Momentum Residual Neural Networks
Home-page: https://github.com/michaelsdr/momentumnet
Download-URL: https://github.com/michaelsdr/momentumnet.git
Maintainer: Michael E. Sander
Maintainer-email: michael.sander1295@yahoo.fr
License: MIT
Platform: any
Classifier: Intended Audience :: Science/Research
Classifier: Intended Audience :: Developers
Classifier: License :: OSI Approved
Classifier: Programming Language :: Python
Classifier: Topic :: Software Development
Classifier: Topic :: Scientific/Engineering
Classifier: Operating System :: Microsoft :: Windows
Classifier: Operating System :: POSIX
Classifier: Operating System :: Unix
Classifier: Operating System :: MacOS
Classifier: Programming Language :: Python :: 3
Requires-Python: >=3.7
License-File: LICENSE
Requires-Dist: numpy (>=1.15)
Requires-Dist: torch (>=1.9.0)
Requires-Dist: torchvision (>=0.9)
Requires-Dist: imageio
Requires-Dist: vit-pytorch
